df_geolocation/__init__.py
df_geolocation/apps.py
df_geolocation/defaults.py
df_geolocation/functions.py
df_geolocation/models.py
df_geolocation/querysets.py
df_geolocation/settings.py
df_geolocation/drf/__init__.py
df_geolocation/drf/serializers.py
django_df_geolocation-0.0.1.dist-info/LICENSE
django_df_geolocation-0.0.1.dist-info/METADATA
django_df_geolocation-0.0.1.dist-info/WHEEL
django_df_geolocation-0.0.1.dist-info/top_level.txt
django_df_geolocation-0.0.1.dist-info/RECORD
