Metadata-Version: 2.1
Name: django-df-geolocation
Version: 0.0.1
Summary: Django DF GEOlocation
Author-email: Apexive OSS <open-source@apexive.com>
License: MIT License
Project-URL: homepage, https://apexive.com/
Classifier: Environment :: Web Environment
Classifier: Framework :: Django
Classifier: Framework :: Django :: 4.2
Classifier: Intended Audience :: Developers
Classifier: License :: OSI Approved :: MIT License
Classifier: Operating System :: OS Independent
Classifier: Programming Language :: Python
Classifier: Programming Language :: Python :: 3
Classifier: Programming Language :: Python :: 3 :: Only
Classifier: Programming Language :: Python :: 3.9
Classifier: Topic :: Internet
Requires-Python: >=3.9
License-File: LICENSE
Requires-Dist: Django >=4.2.0
Requires-Dist: djangorestframework >=3.12.0
Requires-Dist: django-df-api-drf >=1.0.0
Requires-Dist: django-countries
Requires-Dist: django-hashid-field
Provides-Extra: test
Requires-Dist: pytest >=7.4.0 ; extra == 'test'
Requires-Dist: pytest-django ; extra == 'test'
Requires-Dist: django-stubs[compatible-mypy] ; extra == 'test'
Requires-Dist: black >=23.7.0 ; extra == 'test'
Requires-Dist: ruff >=0.0.284 ; extra == 'test'
Requires-Dist: httpretty ; extra == 'test'
